{"amendement": {"@xmlns": "http://schemas.assemblee-nationale.fr/referentiel", "uid": "AMANR5L17PO420120B0325P0D1N000270", "chronotag": "1739874581111", "legislature": "17", "identification": {"numeroLong": "AS270", "numeroOrdreDepot": "270", "prefixeOrganeExamen": "CION-SOC", "numeroRect": "0"}, "examenRef": "EXANR5L17PO420120B0325P0D1", "texteLegislatifRef": "PRJLANR5L17B0325", "triAmendement": "jcaaaaaaaaaaaaaaaaaaaaaaaaaaaaaaaaaaaaaaaaaaaaaaaaaru", "cardinaliteAmdtMultiples": "1", "amendementParentRef": {"@xmlns:xsi": "http://www.w3.org/2001/XMLSchema-instance", "@xsi:nil": "true"}, "signataires": {"auteur": {"typeAuteur": "D\u00e9put\u00e9", "gouvernementRef": {"@xmlns:xsi": "http://www.w3.org/2001/XMLSchema-instance", "@xsi:nil": "true"}, "acteurRef": "PA642847", "groupePolitiqueRef": "PO845425", "auteurRapporteurOrganeRef": {"@xmlns:xsi": "http://www.w3.org/2001/XMLSchema-instance", "@xsi:nil": "true"}}, "cosignataires": {"@xmlns:xsi": "http://www.w3.org/2001/XMLSchema-instance", "@xsi:nil": "true"}, "suffixe": {"@xmlns:xsi": "http://www.w3.org/2001/XMLSchema-instance", "@xsi:nil": "true"}, "libelle": "M.&#160;Bazin"}, "pointeurFragmentTexte": {"partieAmendableRef": {"@xmlns:xsi": "http://www.w3.org/2001/XMLSchema-instance", "@xsi:nil": "true"}, "division": {"titre": "Article 21", "articleDesignationCourte": "APR\u00c8S ART. 21", "articleDesignation": "APR\u00c8S L'ARTICLE 21, ins\u00e9rer l'article suivant:", "type": "ARTICLE", "avant_A_Apres": "Apr\u00e8s", "divisionRattachee": {"@xmlns:xsi": "http://www.w3.org/2001/XMLSchema-instance", "@xsi:nil": "true"}, "articleAdditionnel": "true", "chapitreAdditionnel": "false", "urlDivisionTexteVise": "/17/textes/0325.asp#D_Article_21"}, "amendementStandard": {"alinea": {"@xmlns:xsi": "http://www.w3.org/2001/XMLSchema-instance", "@xsi:nil": "true"}}}, "corps": {"cartoucheInformatif": {"@xmlns:xsi": "http://www.w3.org/2001/XMLSchema-instance", "@xsi:nil": "true"}, "contenuAuteur": {"dispositif": "<p style=\"text-align: justify;\">Avant le 30 septembre 2025, le Gouvernement remet au Parlement un rapport &#x00E9;valuant l&#x2019;impact de l&#x2019;application de l&#x2019;article&nbsp;54 de la loi n&#x00B0;&nbsp;2021&#x2011;1754 du 23 d&#x00E9;cembre 2021 de financement de la s&#x00E9;curit&#x00E9; sociale pour 2022 et la subs&#x00E9;quente opportunit&#x00E9; d&#x2019;&#x00E9;largir la dur&#x00E9;e et l&#x2019;indemnisation du cong&#x00E9; proche aidant.</p>", "avantAppel": {"@xmlns:xsi": "http://www.w3.org/2001/XMLSchema-instance", "@xsi:nil": "true"}, "exposeSommaire": "<p>L&#x2019;acc&#x00E9;l&#x00E9;ration du virage ambulatoire et du virage domiciliaire traduisent la volont&#x00E9; des Fran&#x00E7;ais de vieillir &#x00AB; chez soi &#x00BB;.</p><p>Cette double &#x00E9;volution repose sur l&#x2019;importante participation des aidants familiaux. Ces &#x00E9;volutions ainsi que le vieillissement de la population augmentent la probabilit&#x00E9; qu&#x2019;un aidant familial accompagne plus d&#x2019;une personne au cours de sa vie.</p><p>L&#x2019;enqu&#x00EA;te de l&#x2019;UNAF et du Collectif inter-associatif des aidants familiaux (CIAAF), r&#x00E9;v&#x00E8;le ainsi qu&#x2019;au cours de leur vie, 43 % des aidants accompagnent 2 personnes ou plus. La question de la conciliation des temps entre vie professionnelle, vie d&#x2019;aidant et r&#x00E9;pit se posera avec de plus en plus d&#x2019;acuit&#x00E9;.</p><p>Elle n&#x00E9;cessitera de clarifier les dispositifs de conciliation (cong&#x00E9;s, prise en compte par l&#x2019;entreprise) et de renforcer l&#x2019;offre de r&#x00E9;pit mais aussi d&#x2019;identifier les freins au recours.</p><p>L&#x2019;objet de cet amendement est d&#x2019;&#x00E9;valuer l&#x2019;application de l&#x2019;article 54 de la loi de financement de la s&#x00E9;curit&#x00E9; sociale pour 2022 et la subs&#x00E9;quente opportunit&#x00E9; d&#x2019;&#x00E9;largir la dur&#x00E9;e et l&#x2019;indemnisation du cong&#x00E9; proche aidant, avant l&#x2019;examen du prochain PLFSS.</p>", "annexeExposeSommaire": {"@xmlns:xsi": "http://www.w3.org/2001/XMLSchema-instance", "@xsi:nil": "true"}}}, "cycleDeVie": {"dateDepot": "2024-10-16", "datePublication": "2024-10-24", "soumisArticle40": "false", "etatDesTraitements": {"etat": {"code": "DI", "libelle": "Discut\u00e9"}, "sousEtat": {"code": "DI", "libelle": "Adopt\u00e9"}}, "dateSort": "2024-10-24T23:50:06+02:00", "sort": "Adopt\u00e9"}, "representations": {"representation": {"nom": "PDF", "typeMime": {"type": "application", "subType": "PDF"}, "statutRepresentation": {"verbatim": "true", "canonique": "true", "officielle": "true", "transcription": "false", "enregistrement": "false"}, "repSource": {"@xmlns:xsi": "http://www.w3.org/2001/XMLSchema-instance", "@xsi:nil": "true"}, "offset": {"@xmlns:xsi": "http://www.w3.org/2001/XMLSchema-instance", "@xsi:nil": "true"}, "contenu": {"documentURI": "/base/AMANR5L17PO420120B0325P0D1N000270?format=pdf"}, "dateDispoRepresentation": {"@xmlns:xsi": "http://www.w3.org/2001/XMLSchema-instance", "@xsi:nil": "true"}}}, "seanceDiscussionRef": {"@xmlns:xsi": "http://www.w3.org/2001/XMLSchema-instance", "@xsi:nil": "true"}, "article99": "false", "loiReference": {"codeLoi": "zzz", "divisionCodeLoi": {"@xmlns:xsi": "http://www.w3.org/2001/XMLSchema-instance", "@xsi:nil": "true"}}, "discussionCommune": {"@xmlns:xsi": "http://www.w3.org/2001/XMLSchema-instance", "@xsi:nil": "true"}, "discussionIdentique": {"@xmlns:xsi": "http://www.w3.org/2001/XMLSchema-instance", "@xsi:nil": "true"}, "accordGouvernementDepotHorsDelai": "Sans objet"}}