{"amendement": {"@xmlns": "http://schemas.assemblee-nationale.fr/referentiel", "uid": "AMANR5L17PO838901B0278P0D1N000010", "chronotag": "1739874685134", "legislature": "17", "identification": {"numeroLong": "10", "numeroOrdreDepot": "10", "prefixeOrganeExamen": "AN", "numeroRect": "0"}, "examenRef": "EXANR5L17PO838901B0278P0D1", "texteLegislatifRef": "PIONANR5L17B0278", "triAmendement": "eaaaaaaaaaaaaaaaaaaaaaaaaaaaaaaaaaaaaaaaaaaaaaaaaazzj", "cardinaliteAmdtMultiples": "1", "amendementParentRef": {"@xmlns:xsi": "http://www.w3.org/2001/XMLSchema-instance", "@xsi:nil": "true"}, "signataires": {"auteur": {"typeAuteur": "D\u00e9put\u00e9", "gouvernementRef": {"@xmlns:xsi": "http://www.w3.org/2001/XMLSchema-instance", "@xsi:nil": "true"}, "acteurRef": "PA408578", "groupePolitiqueRef": "PO845425", "auteurRapporteurOrganeRef": {"@xmlns:xsi": "http://www.w3.org/2001/XMLSchema-instance", "@xsi:nil": "true"}}, "cosignataires": {"acteurRef": ["PA642847", "PA840979", "PA793094", "PA722390"]}, "suffixe": {"@xmlns:xsi": "http://www.w3.org/2001/XMLSchema-instance", "@xsi:nil": "true"}, "libelle": "M.&#160;Berger,  M.&#160;Bazin, M.&#160;Le&#160;Fur, M.&#160;Ray et Mme&#160;Corneloup"}, "pointeurFragmentTexte": {"partieAmendableRef": {"@xmlns:xsi": "http://www.w3.org/2001/XMLSchema-instance", "@xsi:nil": "true"}, "division": {"titre": "Article unique", "articleDesignationCourte": "ART. UNIQUE", "articleDesignation": "ARTICLE UNIQUE", "type": "ARTICLE", "avant_A_Apres": "A", "divisionRattachee": {"@xmlns:xsi": "http://www.w3.org/2001/XMLSchema-instance", "@xsi:nil": "true"}, "articleAdditionnel": "false", "chapitreAdditionnel": "false", "urlDivisionTexteVise": "/17/textes/0278.asp#D_Article_unique"}, "amendementStandard": {"alinea": {"@xmlns:xsi": "http://www.w3.org/2001/XMLSchema-instance", "@xsi:nil": "true"}}}, "corps": {"cartoucheInformatif": {"@xmlns:xsi": "http://www.w3.org/2001/XMLSchema-instance", "@xsi:nil": "true"}, "contenuAuteur": {"dispositif": "<p style=\"text-align: justify;\">R&#x00E9;diger ainsi cet article&nbsp;:</p><p style=\"text-align: justify;\">&#x00AB;&nbsp;I. &#x2013; L&#x2019;article&nbsp;6 de la loi n&#x00B0;&nbsp;89&#x2011;462 du 6 juillet 1989 tendant &#x00E0; am&#x00E9;liorer les rapports locatifs et portant modification de la loi n&#x00B0;&nbsp;86&#x2011;1290 du 23 d&#x00E9;cembre 1986, dans sa r&#x00E9;daction r&#x00E9;sultant de l&#x2019;article&nbsp;160 de la loi&nbsp;n&#x00B0;&nbsp;2021&#x2011;1104 du 22 ao&#x00FB;t 2021 portant lutte contre le d&#x00E9;r&#x00E8;glement climatique et renforcement de la r&#x00E9;silience face &#x00E0; ses effets est ainsi modifi&#x00E9;&nbsp;:&nbsp;</p><p style=\"text-align: justify;\">&#x00AB;&nbsp;1&#x00B0;&nbsp;Au 1&#x00B0;&nbsp;, l&#x2019;ann&#x00E9;e&nbsp;:&nbsp;&#x00AB;&nbsp;2025&nbsp;&#x00BB;&nbsp;est remplac&#x00E9;e par l&#x2019;ann&#x00E9;e&nbsp;:&nbsp;&#x00AB;&nbsp;2027&nbsp;&#x00BB;&nbsp;;</p><p style=\"text-align: justify;\">&#x00AB;&nbsp;2&#x00B0;&nbsp;Au 2&#x00B0;&nbsp;, l&#x2019;ann&#x00E9;e&nbsp;:&nbsp;&#x00AB;&nbsp;2028&nbsp;&#x00BB;&nbsp;est remplac&#x00E9;e par l&#x2019;ann&#x00E9;e&nbsp;:&nbsp;&#x00AB;&nbsp;2030&nbsp;&#x00BB;&nbsp;;</p><p style=\"text-align: justify;\">&#x00AB;&nbsp;3&#x00B0;&nbsp;Au 3&#x00B0;&nbsp;, l&#x2019;ann&#x00E9;e&nbsp;:&nbsp;&#x00AB;&nbsp;2034&nbsp;&#x00BB;&nbsp;est remplac&#x00E9;e par l&#x2019;ann&#x00E9;e&nbsp;:&nbsp;&#x00AB;&nbsp;2036&nbsp;&#x00BB;&nbsp;;</p><p style=\"text-align: justify;\">&#x00AB;&nbsp;4&#x00B0;&nbsp;Au <i>a</i>, l&#x2019;ann&#x00E9;e&nbsp;:&nbsp;&#x00AB;&nbsp;2028&nbsp;&#x00BB;&nbsp;est remplac&#x00E9;e par l&#x2019;ann&#x00E9;e&nbsp;:&nbsp;&#x00AB;&nbsp;2030&nbsp;&#x00BB;&nbsp;;</p><p style=\"text-align: justify;\">&#x00AB;&nbsp;5&#x00B0;&nbsp;Au <i>b</i>, l&#x2019;ann&#x00E9;e&nbsp;:&nbsp;&#x00AB;&nbsp;2031&nbsp;&#x00BB;&nbsp;est remplac&#x00E9;e par l&#x2019;ann&#x00E9;e&nbsp;:&nbsp;&#x00AB;&nbsp;2033&nbsp;&#x00BB;.&nbsp;</p><p style=\"text-align: justify;\">&#x00AB;&nbsp;II. &#x2013; Au III de l'article 160 de la n&#x00B0; 2021-1104 du 22 ao&#x00FB;t 2021 portant lutte contre le d&#x00E9;r&#x00E8;glement climatique et renforcement de la r&#x00E9;silience face &#x00E0; ses effets, l&#x2019;ann&#x00E9;e&nbsp;:&nbsp;&#x00AB;&nbsp;2034&nbsp;&#x00BB;&nbsp;est remplac&#x00E9;e par l&#x2019;ann&#x00E9;e&nbsp;:&nbsp;&#x00AB;&nbsp;2036&nbsp;&#x00BB;.</p>", "avantAppel": {"@xmlns:xsi": "http://www.w3.org/2001/XMLSchema-instance", "@xsi:nil": "true"}, "exposeSommaire": "<p>Cet amendement vise &#x00E0; r&#x00E9;&#x00E9;crire l'article 160 de la loi n&#x00B0; 2021-1104 du 22 ao&#x00FB;t 2021 au lieu de simplement le supprimer. En effet, il est tout &#x00E0; fait l&#x00E9;gitime d'&#x00EA;tre inquiet, dans un contexte de crise du logement, que l'article 160 r&#x00E9;dig&#x00E9; dans sa version initiale am&#x00E8;ne &#x00E0; une diminution importante du nombre de biens en location sur le march&#x00E9;. C'est pourquoi nous proposons de conserver l'article 160 en allongeant les d&#x00E9;lai pr&#x00E9;vus pour les biens atteignent les crit&#x00E8;res de d&#x00E9;cence demand&#x00E9;s. &nbsp;</p><p>La suppression de cet article serait un mauvais signal envoy&#x00E9; dans la lutte contre le d&#x00E9;r&#x00E8;glement climatique et contre les passoires thermiques. En effet, le manque d'isolation des b&#x00E2;timents est un des vecteurs principaux du d&#x00E9;r&#x00E8;glement climatique. Le manque d'isolation am&#x00E8;ne &#x00E0; une consommation excessive d'&#x00E9;nergie que ce soit pour le chauffage ou le refroidissement avec, &#x00E0; la cl&#x00E9;, l'&#x00E9;mission suppl&#x00E9;mentaire de gaz &#x00E0; effet de serre lorsque le mode de chauffage utilise des &#x00E9;nergies fossiles.&nbsp;</p><p>Le manque d'isolation met aussi en danger notre syst&#x00E8;me de distribution de l'&#x00E9;lectricit&#x00E9;. En effet, en raison de la hausse de la consommation &#x00E9;lectrique sur certaines plages horaires, les situations de surconsommation sont devenues fr&#x00E9;quentes. Ces situations ont &#x00E9;t&#x00E9; particuli&#x00E8;rement plus nombreuses ces deux derni&#x00E8;res ann&#x00E9;es&nbsp;dans un contexte de crise &#x00E9;nerg&#x00E9;tique.&nbsp;</p><p>Enfin, les personnes vivant dans des passoires thermiques souffrent largement de ces situations. En effet, ce sont souvent des personnes pr&#x00E9;caires qui n'ont pas les moyens de payer la surconsommation d'&#x00E9;nergie qui en d&#x00E9;coule. Les situations de passoire thermique peuvent repr&#x00E9;senter un danger pour la sant&#x00E9;. Par ailleurs, la hausse globale des temp&#x00E9;ratures entra&#x00EE;ne&nbsp;l'effet inverse, avec des appartements, notamment dans les combles, qui deviennent inhabitables en p&#x00E9;riode de fortes chaleurs.&nbsp;</p><p>La suppression de cet article ne r&#x00E9;soudra en rien ces probl&#x00E8;mes et n'incitera pas les propri&#x00E9;taires &#x00E0; faire des travaux pour am&#x00E9;liorer la situation de leurs locataires. L'allongement des diff&#x00E9;rents d&#x00E9;lais&nbsp;de 2 ann&#x00E9;es suppl&#x00E9;mentaires nous semble raisonnable pour mener les travaux de r&#x00E9;novation &#x00E9;nerg&#x00E9;tique.</p><p>Enfin, on peut convenir que certaines situations ne peuvent se pr&#x00EA;ter &#x00E0; des travaux de r&#x00E9;novation &#x00E9;nerg&#x00E9;tique. Nous proposerons donc un amendement de rapport pour &#x00E9;tablir pr&#x00E9;cis&#x00E9;ment les situations d'exception fix&#x00E9;es par d&#x00E9;cret. &nbsp;</p><p>Les r&#x00E8;gles impos&#x00E9;es par cet article, bien qu'imparfaites, demeurent donc utiles pour inciter&nbsp;les propri&#x00E9;taires &#x00E0; r&#x00E9;aliser des travaux&nbsp;dans un objectif de lutte contre le d&#x00E9;r&#x00E8;glement climatique et pour que les logements dans lesquels vivent les locataires soient d&#x00E9;cents.&nbsp;</p>", "annexeExposeSommaire": {"@xmlns:xsi": "http://www.w3.org/2001/XMLSchema-instance", "@xsi:nil": "true"}}}, "cycleDeVie": {"dateDepot": "2024-10-28", "datePublication": "2024-10-31", "soumisArticle40": "true", "etatDesTraitements": {"etat": {"code": "DI", "libelle": "Discut\u00e9"}, "sousEtat": {"code": "DI", "libelle": "Tomb\u00e9"}}, "dateSort": "2024-10-31T23:04:29+01:00", "sort": "Tomb\u00e9"}, "representations": {"representation": {"nom": "PDF", "typeMime": {"type": "application", "subType": "PDF"}, "statutRepresentation": {"verbatim": "true", "canonique": "true", "officielle": "true", "transcription": "false", "enregistrement": "false"}, "repSource": {"@xmlns:xsi": "http://www.w3.org/2001/XMLSchema-instance", "@xsi:nil": "true"}, "offset": {"@xmlns:xsi": "http://www.w3.org/2001/XMLSchema-instance", "@xsi:nil": "true"}, "contenu": {"documentURI": "/base/AMANR5L17PO838901B0278P0D1N000010?format=pdf"}, "dateDispoRepresentation": {"@xmlns:xsi": "http://www.w3.org/2001/XMLSchema-instance", "@xsi:nil": "true"}}}, "seanceDiscussionRef": "RUANR5L17S2025IDS28619", "article99": "false", "loiReference": {"@xmlns:xsi": "http://www.w3.org/2001/XMLSchema-instance", "@xsi:nil": "true"}, "discussionCommune": {"idDiscussion": "27464", "typePosition": "Milieu"}, "discussionIdentique": {"@xmlns:xsi": "http://www.w3.org/2001/XMLSchema-instance", "@xsi:nil": "true"}, "accordGouvernementDepotHorsDelai": "Sans objet"}}