{"amendement": {"@xmlns": "http://schemas.assemblee-nationale.fr/referentiel", "uid": "AMANR5L17PO849474B0481P0D1N001399", "chronotag": "1743013017300", "legislature": "17", "identification": {"numeroLong": "CS1399", "numeroOrdreDepot": "1399", "prefixeOrganeExamen": "CSVIEECO", "numeroRect": "0"}, "examenRef": "EXANR5L17PO419610B0481P0D1", "texteLegislatifRef": "PRJLANR5L17B0481", "triAmendement": "jaaaaaaaaaaaaaaaaaaaaaaaaaaaaaaaaaaaaaaaaaaaaaaaaabgi", "cardinaliteAmdtMultiples": "1", "amendementParentRef": {"@xmlns:xsi": "http://www.w3.org/2001/XMLSchema-instance", "@xsi:nil": "true"}, "signataires": {"auteur": {"typeAuteur": "Rapporteur", "gouvernementRef": {"@xmlns:xsi": "http://www.w3.org/2001/XMLSchema-instance", "@xsi:nil": "true"}, "acteurRef": "PA607395", "groupePolitiqueRef": "PO845407", "auteurRapporteurOrganeRef": {"@xmlns:xsi": "http://www.w3.org/2001/XMLSchema-instance", "@xsi:nil": "true"}}, "cosignataires": {"@xmlns:xsi": "http://www.w3.org/2001/XMLSchema-instance", "@xsi:nil": "true"}, "suffixe": {"@xmlns:xsi": "http://www.w3.org/2001/XMLSchema-instance", "@xsi:nil": "true"}, "libelle": "M.&#160;Travert, rapporteur"}, "pointeurFragmentTexte": {"partieAmendableRef": {"@xmlns:xsi": "http://www.w3.org/2001/XMLSchema-instance", "@xsi:nil": "true"}, "division": {"titre": "Article 19", "articleDesignationCourte": "ART. 19", "articleDesignation": "ARTICLE 19", "type": "ARTICLE", "avant_A_Apres": "A", "divisionRattachee": {"@xmlns:xsi": "http://www.w3.org/2001/XMLSchema-instance", "@xsi:nil": "true"}, "articleAdditionnel": "false", "chapitreAdditionnel": "false", "urlDivisionTexteVise": "/17/textes/0481.asp#D_Article_19"}, "amendementStandard": {"alinea": {"avant_A_Apres": "Apres", "numero": "6", "alineaDesignation": "Apr\u00e8s l'alin\u00e9a 6"}}}, "corps": {"cartoucheInformatif": {"@xmlns:xsi": "http://www.w3.org/2001/XMLSchema-instance", "@xsi:nil": "true"}, "contenuAuteur": {"dispositif": "<p style=\"text-align: justify;\">Apr&#x00E8;s l&#x2019;alin&#x00E9;a&nbsp;6, ins&#x00E9;rer l&#x2019;alin&#x00E9;a suivant&nbsp;: </p><p style=\"text-align: justify;\">&#x00AB;&nbsp;1&#x00B0;&nbsp;<i>bis</i>&nbsp;Apr&#x00E8;s le mot&nbsp;: &#x00AB;&nbsp;unique&nbsp;&#x00BB;, la fin de l&#x2019;article L.&nbsp;133&#x2011;12 est ainsi r&#x00E9;dig&#x00E9;e&nbsp;: &#x00AB;&nbsp;r&#x00E9;alis&#x00E9;e conform&#x00E9;ment aux articles L.&nbsp;123&#x2011;1-A &#x00E0; L.&nbsp;127&#x2011;10 du code de l&#x2019;environnement, sous r&#x00E9;serve des dispositions des deux derniers alin&#x00E9;as du I de l&#x2019;article L.&nbsp;181&#x2011;10 du m&#x00EA;me code.&nbsp;&#x00BB;&nbsp;;</p>", "avantAppel": {"@xmlns:xsi": "http://www.w3.org/2001/XMLSchema-instance", "@xsi:nil": "true"}, "exposeSommaire": "<p style=\"text-align: justify;\">L&#x2019;article L.&nbsp;133&#x2011;12 du code minier d&#x00E9;finit les conditions de r&#x00E9;alisation de l&#x2019;enqu&#x00EA;te publique lorsque la demande de titre minier et la demande d&#x2019;autorisation de travaux sont pr&#x00E9;sent&#x00E9;es simultan&#x00E9;ment&nbsp;: en renvoyant &#x00E0; l&#x2019;article L.&nbsp;162&#x2011;7 du m&#x00EA;me code, il pr&#x00E9;voit, dans ce cas, la r&#x00E9;alisation d&#x2019;une enqu&#x00EA;te publique unique. Toutefois, l&#x2019;article L.&nbsp;162&#x2011;7 a &#x00E9;t&#x00E9; abrog&#x00E9;, au 1<sup>er</sup> juillet 2023, par l&#x2019;article&nbsp;2 de l&#x2019;ordonnance n&#x00B0;&nbsp;2022&#x2011;534 du 13 avril 2022.</p><p style=\"text-align: justify;\">Le pr&#x00E9;sent amendement conduit donc &#x00E0; remplacer cette r&#x00E9;f&#x00E9;rence, devenue sans objet, par les dispositions de droit commun du code de l&#x2019;environnement encadrant l&#x2019;enqu&#x00EA;te publique unique. Ces dispositions s&#x2019;appliqueront sous r&#x00E9;serve des modalit&#x00E9;s de participation du public pr&#x00E9;vue en cas d&#x2019;autorisation environnementale&nbsp;: l&#x2019;enqu&#x00EA;te publique unique, d&#x2019;une dur&#x00E9;e d&#x2019;un mois, ne sera alors possible que si l&#x2019;enqu&#x00EA;te n&#x2019;a pas encore &#x00E9;t&#x00E9; r&#x00E9;alis&#x00E9;e pour l&#x2019;une et l&#x2019;autre des demandes, d&#x2019;une part, et le p&#x00E9;titionnaire pourra demander &#x00E0; ce qu&#x2019;il soit d&#x00E9;rog&#x00E9; &#x00E0; cette modalit&#x00E9; de participation du public, d&#x2019;autre part.</p><p style=\"text-align: justify;\">&nbsp;</p>", "annexeExposeSommaire": {"@xmlns:xsi": "http://www.w3.org/2001/XMLSchema-instance", "@xsi:nil": "true"}}}, "cycleDeVie": {"dateDepot": "2025-03-21", "datePublication": "2025-03-26", "soumisArticle40": "false", "etatDesTraitements": {"etat": {"code": "DI", "libelle": "Discut\u00e9"}, "sousEtat": {"code": "DI", "libelle": "Adopt\u00e9"}}, "dateSort": "2025-03-26T19:16:37+01:00", "sort": "Adopt\u00e9"}, "representations": {"representation": {"nom": "PDF", "typeMime": {"type": "application", "subType": "PDF"}, "statutRepresentation": {"verbatim": "true", "canonique": "true", "officielle": "true", "transcription": "false", "enregistrement": "false"}, "repSource": {"@xmlns:xsi": "http://www.w3.org/2001/XMLSchema-instance", "@xsi:nil": "true"}, "offset": {"@xmlns:xsi": "http://www.w3.org/2001/XMLSchema-instance", "@xsi:nil": "true"}, "contenu": {"documentURI": "/base/AMANR5L17PO849474B0481P0D1N001399?format=pdf"}, "dateDispoRepresentation": {"@xmlns:xsi": "http://www.w3.org/2001/XMLSchema-instance", "@xsi:nil": "true"}}}, "seanceDiscussionRef": {"@xmlns:xsi": "http://www.w3.org/2001/XMLSchema-instance", "@xsi:nil": "true"}, "article99": "false", "loiReference": {"@xmlns:xsi": "http://www.w3.org/2001/XMLSchema-instance", "@xsi:nil": "true"}, "discussionCommune": {"@xmlns:xsi": "http://www.w3.org/2001/XMLSchema-instance", "@xsi:nil": "true"}, "discussionIdentique": {"@xmlns:xsi": "http://www.w3.org/2001/XMLSchema-instance", "@xsi:nil": "true"}, "accordGouvernementDepotHorsDelai": "Sans objet"}}