{"amendement": {"@xmlns": "http://schemas.assemblee-nationale.fr/referentiel", "uid": "AMANR5L17PO59048B0324P2D1N001164", "chronotag": "1739874544489", "legislature": "17", "identification": {"numeroLong": "II-CF1164", "numeroOrdreDepot": "1164", "prefixeOrganeExamen": "CION_FIN", "numeroRect": "0"}, "examenRef": "EXANR5L17PO59048B0324P2D1", "texteLegislatifRef": "PRJLANR5L17B0324", "triAmendement": "ariaaaaaaaaaaaaaaaaaaaaaaaaaaaaaaaaaaaaaaaaaaaaaaaaczzro", "cardinaliteAmdtMultiples": "1", "amendementParentRef": {"@xmlns:xsi": "http://www.w3.org/2001/XMLSchema-instance", "@xsi:nil": "true"}, "signataires": {"auteur": {"typeAuteur": "D\u00e9put\u00e9", "gouvernementRef": {"@xmlns:xsi": "http://www.w3.org/2001/XMLSchema-instance", "@xsi:nil": "true"}, "acteurRef": "PA643175", "groupePolitiqueRef": "PO840056", "auteurRapporteurOrganeRef": {"@xmlns:xsi": "http://www.w3.org/2001/XMLSchema-instance", "@xsi:nil": "true"}}, "cosignataires": {"@xmlns:xsi": "http://www.w3.org/2001/XMLSchema-instance", "@xsi:nil": "true"}, "suffixe": {"@xmlns:xsi": "http://www.w3.org/2001/XMLSchema-instance", "@xsi:nil": "true"}, "libelle": "Mme&#160;Dupont"}, "pointeurFragmentTexte": {"partieAmendableRef": {"@xmlns:xsi": "http://www.w3.org/2001/XMLSchema-instance", "@xsi:nil": "true"}, "division": {"titre": "\u00c9TAT B", "articleDesignationCourte": "ART. 42", "articleDesignation": "ARTICLE 42", "type": "ANNEXE", "avant_A_Apres": "A", "divisionRattachee": "ARTICLE 42", "articleAdditionnel": "false", "chapitreAdditionnel": "false", "urlDivisionTexteVise": "/17/textes/0324C.asp#D_Etat_B"}, "missionVisee": {"codeEtat": "B", "codeMissionMinefi": "DB", "libelleMission": "\u00c9conomie", "missionRef": "2864"}}, "corps": {"cartoucheInformatif": {"@xmlns:xsi": "http://www.w3.org/2001/XMLSchema-instance", "@xsi:nil": "true"}, "contenuAuteur": {"dispositifAmdtCreditPLF": {"listeProgrammes": {"programme": [{"libelle": "D\u00e9veloppement des entreprises et r\u00e9gulations", "programmeRef": "399554", "autorisationEngagement": "0", "creditPaiement": "0", "action": "modification", "lignesCredits": {"@xmlns:xsi": "http://www.w3.org/2001/XMLSchema-instance", "@xsi:nil": "true"}}, {"libelle": "Plan France Tr\u00e8s haut d\u00e9bit", "programmeRef": "399556", "autorisationEngagement": "0", "creditPaiement": "0", "action": "modification", "lignesCredits": {"@xmlns:xsi": "http://www.w3.org/2001/XMLSchema-instance", "@xsi:nil": "true"}}, {"libelle": "Statistiques et \u00e9tudes \u00e9conomiques", "programmeRef": "399558", "autorisationEngagement": "-5000000", "creditPaiement": "-5000000", "action": "modification", "lignesCredits": {"@xmlns:xsi": "http://www.w3.org/2001/XMLSchema-instance", "@xsi:nil": "true"}}, {"libelle": "Strat\u00e9gies \u00e9conomiques", "programmeRef": "399560", "autorisationEngagement": "5000000", "creditPaiement": "5000000", "action": "modification", "lignesCredits": {"@xmlns:xsi": "http://www.w3.org/2001/XMLSchema-instance", "@xsi:nil": "true"}}, {"libelle": "Financement des op\u00e9rations patrimoniales en 2025 sur le compte d'affectation sp\u00e9ciale \u00ab Participations financi\u00e8res de l'\u00c9tat \u00bb", "programmeRef": "399562", "autorisationEngagement": "0", "creditPaiement": "0", "action": "modification", "lignesCredits": {"@xmlns:xsi": "http://www.w3.org/2001/XMLSchema-instance", "@xsi:nil": "true"}}]}, "soldeAE": "0", "soldeCP": "0", "cpEgalAe": "true"}, "avantAppel": {"@xmlns:xsi": "http://www.w3.org/2001/XMLSchema-instance", "@xsi:nil": "true"}, "exposeSommaire": "<p>L'&#x00E9;conomie sociale et solidaire (ESS) rassemble les entreprises qui cherchent &#x00E0; concilier solidarit&#x00E9;, performances &#x00E9;conomiques et utilit&#x00E9; sociale. Dans l'&#x00E9;conomie fran&#x00E7;aise, l'ESS repr&#x00E9;sente 10 % du PIB et pr&#x00E8;s de 14 % des emplois priv&#x00E9;s.</p><p>Le soutien financier apport&#x00E9; par l'Etat &#x00E0; l'ESS permet le d&#x00E9;veloppement de la fili&#x00E8;re, &#x00E0; travers notamment les chambres r&#x00E9;gionales de l'&#x00E9;conomie sociale et solidaire (CRESS). Ce programme finance aussi le dispositif local d'accompagnement (DLA) et les p&#x00F4;les territoriaux de coop&#x00E9;ration &#x00E9;conomique (PTCE).</p><p>Le pr&#x00E9;sent PLF r&#x00E9;duit de 25% les cr&#x00E9;dits de paiement d&#x00E9;di&#x00E9;s &#x00E0; l'ESS, le budget s'&#x00E9;l&#x00E8;verait &#x00E0; 17 millions d'euros en 2025.</p><p>Cet amendement propose de revaloriser de 5 millions d'euros les financements d&#x00E9;di&#x00E9;s &#x00E0; l'&#x00E9;conomie sociale, solidaire et responsable en augmentant les cr&#x00E9;dits de l'action 4 du programme n&#x00B0; 305 &#x00AB;&nbsp;Strat&#x00E9;gies &#x00E9;conomiques&nbsp;&#x00BB;, AE = CP. Afin de r&#x00E9;pondre aux obligations fix&#x00E9;es par la LOLF et conserver un solde &#x00E0; z&#x00E9;ro sur cette mission, il minore du m&#x00EA;me montant l'action&nbsp;9 du programme n&#x00B0;&nbsp;220 &#x00AB;&nbsp;Statistiques et &#x00E9;tudes &#x00E9;conomiques&nbsp;&#x00BB;, AE = CP.</p><p>Ce transfert de cr&#x00E9;dits en d&#x00E9;faveur de&nbsp;l'action 9 du programme n&#x00B0; 220 &#x00AB;&nbsp;Statistiques et &#x00E9;tudes &#x00E9;conomiques &#x00BB; n&#x2019;est pas le reflet d&#x2019;une moindre importance accord&#x00E9;e audit programme mais r&#x00E9;pond aux r&#x00E8;gles de r&#x00E9;daction des amendements en ne cr&#x00E9;ant pas de charges suppl&#x00E9;mentaires. L'auteure du pr&#x00E9;sent amendement &#x00E9;met par ailleurs le souhait d'une lev&#x00E9;e de gage par le Gouvernement.</p>", "annexeExposeSommaire": {"@xmlns:xsi": "http://www.w3.org/2001/XMLSchema-instance", "@xsi:nil": "true"}}}, "cycleDeVie": {"dateDepot": "2024-10-24", "datePublication": "2024-11-15", "soumisArticle40": "false", "etatDesTraitements": {"etat": {"code": "DI", "libelle": "Discut\u00e9"}, "sousEtat": {"code": "DI", "libelle": "Tomb\u00e9"}}, "dateSort": "2024-10-28T16:49:52+01:00", "sort": "Tomb\u00e9"}, "representations": {"representation": {"nom": "PDF", "typeMime": {"type": "application", "subType": "PDF"}, "statutRepresentation": {"verbatim": "true", "canonique": "true", "officielle": "true", "transcription": "false", "enregistrement": "false"}, "repSource": {"@xmlns:xsi": "http://www.w3.org/2001/XMLSchema-instance", "@xsi:nil": "true"}, "offset": {"@xmlns:xsi": "http://www.w3.org/2001/XMLSchema-instance", "@xsi:nil": "true"}, "contenu": {"documentURI": "/base/AMANR5L17PO59048B0324P2D1N001164?format=pdf"}, "dateDispoRepresentation": {"@xmlns:xsi": "http://www.w3.org/2001/XMLSchema-instance", "@xsi:nil": "true"}}}, "seanceDiscussionRef": {"@xmlns:xsi": "http://www.w3.org/2001/XMLSchema-instance", "@xsi:nil": "true"}, "article99": "false", "loiReference": {"codeLoi": "4", "divisionCodeLoi": "4"}, "discussionCommune": {"idDiscussion": "27156", "typePosition": "Milieu"}, "discussionIdentique": {"@xmlns:xsi": "http://www.w3.org/2001/XMLSchema-instance", "@xsi:nil": "true"}, "accordGouvernementDepotHorsDelai": "Sans objet"}}