{"amendement": {"@xmlns": "http://schemas.assemblee-nationale.fr/referentiel", "uid": "AMANR5L17PO838901B0324P1D1N002330", "chronotag": "1739874611366", "legislature": "17", "identification": {"numeroLong": "I-2330", "numeroOrdreDepot": "2330", "prefixeOrganeExamen": "AN", "numeroRect": "0"}, "examenRef": "EXANR5L17PO838901B0324P1D1", "texteLegislatifRef": "PRJLANR5L17B0324", "triAmendement": "cfaaaaaaaaaaaaaaaaaaaaaaaaaaaaaaaaaaaaaaaaaaaaaaaaac", "cardinaliteAmdtMultiples": "1", "amendementParentRef": {"@xmlns:xsi": "http://www.w3.org/2001/XMLSchema-instance", "@xsi:nil": "true"}, "signataires": {"auteur": {"typeAuteur": "D\u00e9put\u00e9", "gouvernementRef": {"@xmlns:xsi": "http://www.w3.org/2001/XMLSchema-instance", "@xsi:nil": "true"}, "acteurRef": "PA841515", "groupePolitiqueRef": "PO845413", "auteurRapporteurOrganeRef": {"@xmlns:xsi": "http://www.w3.org/2001/XMLSchema-instance", "@xsi:nil": "true"}}, "cosignataires": {"acteurRef": ["PA795228", "PA793262", "PA794906", "PA794138", "PA795588", "PA795084", "PA842105", "PA841657", "PA720430", "PA793772", "PA795616", "PA793444", "PA794938", "PA795318", "PA841023", "PA796090", "PA793912", "PA842187", "PA842037", "PA791812", "PA793736", "PA721202", "PA795136", "PA793464", "PA842155", "PA795200", "PA795844", "PA841251", "PA794786", "PA794870", "PA796070", "PA795310", "PA794478", "PA841947", "PA794082", "PA794130", "PA720846", "PA841729", "PA795516", "PA795672", "PA795108", "PA795298", "PA791824", "PA842029", "PA793532", "PA795746", "PA342384", "PA795422", "PA794686", "PA841215", "PA795482", "PA610654", "PA841191", "PA721960", "PA793872", "PA720892", "PA817211", "PA793756", "PA796062", "PA719578", "PA721062", "PA841845", "PA795982", "PA795466", "PA793744", "PA720952", "PA794106", "PA795164", "PA795596"]}, "suffixe": {"@xmlns:xsi": "http://www.w3.org/2001/XMLSchema-instance", "@xsi:nil": "true"}, "libelle": "M.&#160;Le&#160;Coq,  Mme&#160;Abomangoli, M.&#160;Alexandre, M.&#160;Amard, Mme&#160;Amiot, Mme&#160;Amrani, M.&#160;Arenas, M.&#160;Arnault, Mme&#160;Belouassa-Cherifi, M.&#160;Bernalicis, M.&#160;Bex, M.&#160;Bilongo, M.&#160;Bompard, M.&#160;Boumertit, M.&#160;Boyard, M.&#160;Cadalen, M.&#160;Caron, M.&#160;Carri&#232;re, Mme&#160;Cathala, M.&#160;Cernon, Mme&#160;Chikirou, M.&#160;Clouet, M.&#160;Coquerel, M.&#160;Coulomme, M.&#160;Delogu, M.&#160;Diouara, Mme&#160;Dufour, Mme&#160;Erodi, Mme&#160;Feld, M.&#160;Fernandes, Mme&#160;Ferrer, M.&#160;Gaillard, Mme&#160;Guett&#233;, M.&#160;Guiraud, Mme&#160;Hamdane, Mme&#160;Hignet, M.&#160;Kerbrat, M.&#160;Lachaud, M.&#160;Lahmar, M.&#160;Laisney, M.&#160;Le&#160;Gall, Mme&#160;Leboucher, M.&#160;Legavre, Mme&#160;Legrain, Mme&#160;Lejeune, Mme&#160;Lepvraud, M.&#160;L&#233;aument, Mme&#160;&#201;lisa&#160;Martin, M.&#160;Maudet, Mme&#160;Maximi, Mme&#160;Mesmeur, Mme&#160;Manon&#160;Meunier, M.&#160;Nilor, Mme&#160;Nosb&#233;, Mme&#160;Obono, Mme&#160;Oziol, Mme&#160;Panot, M.&#160;Pilato, M.&#160;Piquemal, M.&#160;Portes, M.&#160;Prud&apos;homme, M.&#160;Ratenon, M.&#160;Saint-Martin, M.&#160;Saintoul, Mme&#160;Soudais, Mme&#160;Stambach-Terrenoir, M.&#160;Tach&#233;, Mme&#160;Taurinya, Mme&#160;Trouv&#233; et M.&#160;Vannier"}, "pointeurFragmentTexte": {"partieAmendableRef": {"@xmlns:xsi": "http://www.w3.org/2001/XMLSchema-instance", "@xsi:nil": "true"}, "division": {"titre": "Article 12", "articleDesignationCourte": "APR\u00c8S ART. 12", "articleDesignation": "APR\u00c8S L'ARTICLE 12, ins\u00e9rer l'article suivant:", "type": "ARTICLE", "avant_A_Apres": "Apr\u00e8s", "divisionRattachee": {"@xmlns:xsi": "http://www.w3.org/2001/XMLSchema-instance", "@xsi:nil": "true"}, "articleAdditionnel": "true", "chapitreAdditionnel": "false", "urlDivisionTexteVise": "/17/textes/0324A.asp#D_Article_12"}, "amendementStandard": {"alinea": {"@xmlns:xsi": "http://www.w3.org/2001/XMLSchema-instance", "@xsi:nil": "true"}}}, "corps": {"cartoucheInformatif": {"@xmlns:xsi": "http://www.w3.org/2001/XMLSchema-instance", "@xsi:nil": "true"}, "contenuAuteur": {"dispositif": "<p style=\"text-align: justify;\">L&#x2019;article&nbsp;209&#x2011;0 B du code g&#x00E9;n&#x00E9;ral des imp&#x00F4;ts est abrog&#x00E9;.</p>", "avantAppel": {"@xmlns:xsi": "http://www.w3.org/2001/XMLSchema-instance", "@xsi:nil": "true"}, "exposeSommaire": "<p>Cet amendement du groupe LFI-NFP vise &#x00E0; supprimer le dispositif d&#x00E9;rogatoire de taxation au tonnage dont b&#x00E9;n&#x00E9;ficie le secteur du transport maritime.</p><p>Cet avantage fiscal, accord&#x00E9; par la France depuis 2003, permet de calculer l'assiette de l'imp&#x00F4;t sur les soci&#x00E9;t&#x00E9;s &#x00E0; partir du tonnage de la flotte et non des b&#x00E9;n&#x00E9;fices r&#x00E9;els de la compagnie. De fait, les armateurs fran&#x00E7;ais se retrouvent exon&#x00E9;r&#x00E9;s d'imp&#x00F4;t sur les soci&#x00E9;t&#x00E9;s. Cette mesure pr&#x00E9;tendait d&#x00E9;fendre les armateurs europ&#x00E9;ens contre la concurrence &#x00E9;trang&#x00E8;re, et &#x00E9;viter l'exil fiscal par usage de pavillons &#x00E9;tranger. Depuis plus de vingt ans, elle est en &#x00E9;chec : la part des navires battant pavillon dans les &#x00C9;tats membres de l&#x2019;Union europ&#x00E9;enne a d&#x00E9;croch&#x00E9; par rapport &#x00E0; l&#x2019;&#x00E9;volution de l&#x2019;ensemble de la flotte mondiale : +3,4% contre +7% entre 2017 et 2022.</p><p>A contrario, ce dispositif a permis aux compagnies de transport maritime, et notamment au groupe CMA-CGM, de d&#x00E9;fiscaliser leurs b&#x00E9;n&#x00E9;fices records en 2021 et en 2022. En 2022, le groupe CMA-CGM a enregistr&#x00E9; 23,5 milliards d'euros de b&#x00E9;n&#x00E9;fices nets, le plus gros b&#x00E9;n&#x00E9;fice annuel jamais r&#x00E9;alis&#x00E9; par une soci&#x00E9;t&#x00E9; fran&#x00E7;aise, devan&#x00E7;ant les superprofits de TotalEnergies. Ces b&#x00E9;n&#x00E9;fices exceptionnels ont permis au groupe CMA-CGM et &#x00E0; son patron Rodolphe Saad&#x00E9; de se constituer un v&#x00E9;ritable empire logistique transnational, s&#x2019;&#x00E9;tendant &#x00E9;galement aux m&#x00E9;dias : apr&#x00E8;s La Provence, et La Tribune, c'est RMC et BFM qui passent d&#x00E9;sormais sous la coupe de Monsieur Saad&#x00E9;.</p><p>Cette bienveillance pour la concentration des richesses et des empires m&#x00E9;diatiques a un co&#x00FB;t croissant pour nos finances publiques : le rapport de R&#x00E9;sultat et gestion du budget de l&#x2019;&#x00C9;tat en 2023 de la Cour des comptes l'&#x00E9;value &#x00E0; 5,6 milliards d'euros en 2023, pour \"seulement\" 3,8 milliards d'euros en 2022. En une seule ann&#x00E9;e, le co&#x00FB;t de cette niche, troisi&#x00E8;me d&#x00E9;pense fiscale du pays, a donc augment&#x00E9; de pr&#x00E8;s de 50% ! Il est grand temps d'y mettre un terme.</p><p>Au vu de l&#x2019;inefficacit&#x00E9; de ce dispositif, et du co&#x00FB;t important qu'il repr&#x00E9;sente, nous proposons donc d'assujettir les compagnies de transport maritime au droit commun de l'imp&#x00F4;t sur les soci&#x00E9;t&#x00E9;s et de mettre ainsi un terme &#x00E0; un avantage fiscal injustifi&#x00E9;, inutile et co&#x00FB;teux.</p>", "annexeExposeSommaire": {"@xmlns:xsi": "http://www.w3.org/2001/XMLSchema-instance", "@xsi:nil": "true"}}}, "cycleDeVie": {"dateDepot": "2024-10-18", "datePublication": "2024-10-26", "soumisArticle40": "true", "etatDesTraitements": {"etat": {"code": "DI", "libelle": "Discut\u00e9"}, "sousEtat": {"code": "DI", "libelle": "Tomb\u00e9"}}, "dateSort": {"@xmlns:xsi": "http://www.w3.org/2001/XMLSchema-instance", "@xsi:nil": "true"}, "sort": "Tomb\u00e9"}, "representations": {"representation": {"nom": "PDF", "typeMime": {"type": "application", "subType": "PDF"}, "statutRepresentation": {"verbatim": "true", "canonique": "true", "officielle": "true", "transcription": "false", "enregistrement": "false"}, "repSource": {"@xmlns:xsi": "http://www.w3.org/2001/XMLSchema-instance", "@xsi:nil": "true"}, "offset": {"@xmlns:xsi": "http://www.w3.org/2001/XMLSchema-instance", "@xsi:nil": "true"}, "contenu": {"documentURI": "/base/AMANR5L17PO838901B0324P1D1N002330?format=pdf"}, "dateDispoRepresentation": {"@xmlns:xsi": "http://www.w3.org/2001/XMLSchema-instance", "@xsi:nil": "true"}}}, "seanceDiscussionRef": {"@xmlns:xsi": "http://www.w3.org/2001/XMLSchema-instance", "@xsi:nil": "true"}, "article99": "false", "loiReference": {"codeLoi": "CGI", "divisionCodeLoi": "209-0 B"}, "discussionCommune": {"@xmlns:xsi": "http://www.w3.org/2001/XMLSchema-instance", "@xsi:nil": "true"}, "discussionIdentique": {"@xmlns:xsi": "http://www.w3.org/2001/XMLSchema-instance", "@xsi:nil": "true"}, "accordGouvernementDepotHorsDelai": "Sans objet"}}