{"amendement": {"@xmlns": "http://schemas.assemblee-nationale.fr/referentiel", "uid": "AMANR5L17PO838901B0324P2D1N000151", "chronotag": "1740392251516", "legislature": "17", "identification": {"numeroLong": "II-151", "numeroOrdreDepot": "151", "prefixeOrganeExamen": "AN", "numeroRect": "0"}, "examenRef": "EXANR5L17PO838901B0324P2D1", "texteLegislatifRef": "PRJLANR5L17B0324", "triAmendement": "ccoaaaaaaaaaaaaaaaaaaaaaaaaaaaaaaaaaaaaaaaaaaaaaaaal", "cardinaliteAmdtMultiples": "1", "amendementParentRef": {"@xmlns:xsi": "http://www.w3.org/2001/XMLSchema-instance", "@xsi:nil": "true"}, "signataires": {"auteur": {"typeAuteur": "D\u00e9put\u00e9", "gouvernementRef": {"@xmlns:xsi": "http://www.w3.org/2001/XMLSchema-instance", "@xsi:nil": "true"}, "acteurRef": "PA842211", "groupePolitiqueRef": "PO845419", "auteurRapporteurOrganeRef": {"@xmlns:xsi": "http://www.w3.org/2001/XMLSchema-instance", "@xsi:nil": "true"}}, "cosignataires": {"acteurRef": ["PA840171", "PA607553", "PA841367", "PA841919", "PA794094", "PA841717", "PA721062", "PA795820", "PA774960", "PA1008", "PA774962", "PA840829", "PA841091", "PA606793", "PA794494"]}, "suffixe": {"@xmlns:xsi": "http://www.w3.org/2001/XMLSchema-instance", "@xsi:nil": "true"}, "libelle": "Mme&#160;Bellay,  M.&#160;Emmanuel&#160;Gr&#233;goire, M.&#160;Potier, M.&#160;Proen&#231;a, Mme&#160;Diop, M.&#160;Bouloux, Mme&#160;Runel, M.&#160;Ratenon, M.&#160;Nadeau, Mme&#160;Santiago, M.&#160;David, Mme&#160;Lebon, M.&#160;Barusseau, M.&#160;Simion, M.&#160;Baumel et M.&#160;Vicot"}, "pointeurFragmentTexte": {"partieAmendableRef": {"@xmlns:xsi": "http://www.w3.org/2001/XMLSchema-instance", "@xsi:nil": "true"}, "division": {"titre": "\u00c9TAT B", "articleDesignationCourte": "ART. 42", "articleDesignation": "ARTICLE 42", "type": "ANNEXE", "avant_A_Apres": "A", "divisionRattachee": "ARTICLE 42", "articleAdditionnel": "false", "chapitreAdditionnel": "false", "urlDivisionTexteVise": "/17/textes/0324C.asp#D_Etat_B"}, "missionVisee": {"codeEtat": "B", "codeMissionMinefi": "OA", "libelleMission": "Outre-mer", "missionRef": "2880"}}, "corps": {"cartoucheInformatif": "Sous r\u00e9serve de son traitement par les services de l'Assembl\u00e9e nationale et de sa recevabilit\u00e9", "contenuAuteur": {"dispositifAmdtCreditPLF": {"listeProgrammes": {"programme": [{"libelle": "Emploi outre-mer", "programmeRef": "427032", "autorisationEngagement": "-1500000", "creditPaiement": "-1500000", "action": "modification", "lignesCredits": {"@xmlns:xsi": "http://www.w3.org/2001/XMLSchema-instance", "@xsi:nil": "true"}}, {"libelle": "Conditions de vie outre-mer", "programmeRef": "427034", "autorisationEngagement": "1500000", "creditPaiement": "1500000", "action": "modification", "lignesCredits": {"@xmlns:xsi": "http://www.w3.org/2001/XMLSchema-instance", "@xsi:nil": "true"}}]}, "soldeAE": "0", "soldeCP": "0", "cpEgalAe": "true"}, "avantAppel": {"@xmlns:xsi": "http://www.w3.org/2001/XMLSchema-instance", "@xsi:nil": "true"}, "exposeSommaire": "<p>Cet amendement vise &#x00E0; instaurer des mesures de suivi m&#x00E9;dical syst&#x00E9;matique des personnes &#x00E0; risque, &#x00E0; renforcer la pr&#x00E9;vention dans les zones concern&#x00E9;es, et &#x00E0; d&#x00E9;velopper des syst&#x00E8;mes d&#x2019;alerte efficaces pour informer les populations des risques li&#x00E9;s aux &#x00E9;manations toxiques. De plus, il propose de financer des &#x00E9;tudes suppl&#x00E9;mentaires sur les effets &#x00E0; long terme de ces gaz sur la sant&#x00E9; publique.<br>&nbsp;<br>Les &#x00E9;chouements massifs de sargasses sur les c&#x00F4;tes des territoires ultramarins, notamment en Guadeloupe et en Martinique, repr&#x00E9;sentent une v&#x00E9;ritable crise environnementale et sanitaire. Ces algues lib&#x00E8;rent des gaz toxiques tels que l&#x2019;hydrog&#x00E8;ne sulfur&#x00E9; et l&#x2019;ammoniac, qui constituent un risque majeur pour la sant&#x00E9; des populations locales, en particulier les personnes vuln&#x00E9;rables (enfants, personnes &#x00E2;g&#x00E9;es, personnes souffrant de troubles respiratoires). Face &#x00E0; cette urgence, le Plan Sargasses, initi&#x00E9; par Nicolas Hulot en 2018, a pos&#x00E9; les bases d'une action nationale pour lutter contre cette crise avec un plan pluriannuel. Ce plan a pr&#x00E9;vu des mesures d&#x2019;urgence pour le ramassage des algues et des financements pour la recherche sur leur gestion.<br>&nbsp;<br>Cependant, bien que le Plan Sargasses ait permis de progresser dans la gestion des &#x00E9;chouements, alors que l&#x2019;&#x00E9;chouement des sargasses n&#x2019;a toujours pas &#x00E9;t&#x00E9; durablement endigu&#x00E9;, ce plan ne couvre pas pleinement les enjeux sanitaires auxquels font face les populations expos&#x00E9;es aux &#x00E9;manations toxiques. Les effets sur la sant&#x00E9;, &#x00E0; court et long terme, demeurent insuffisamment &#x00E9;tudi&#x00E9;s et encadr&#x00E9;s. C&#x2019;est pourquoi cet amendement vise &#x00E0; compl&#x00E9;ter ce dispositif en instaurant des mesures de pr&#x00E9;vention sp&#x00E9;cifiques et un suivi m&#x00E9;dical syst&#x00E9;matique des personnes &#x00E0; risque dans les zones les plus touch&#x00E9;es par les &#x00E9;chouements de sargasses.<br>&nbsp;<br>Par cet amendement, il est donc propos&#x00E9;, &#x00E0; cette fin, d&#x2019;augmenter de&nbsp;1,5 millions d&#x2019;euros de cr&#x00E9;dits en AE et en CP l&#x2019;action 04 &#x2013; Sanitaire, social, culture, jeunesse et sports du programme 123. Cette augmentation sera compens&#x00E9;e, pour les besoins de la recevabilit&#x00E9; financi&#x00E8;re de l&#x2019;amendement, par une baisse du m&#x00EA;me montant de l&#x2019;action n&#x00B0;&nbsp;01 du programme 138&nbsp;: &#x00AB;&nbsp;Emploi outre-mer&nbsp;&#x00BB;. <br>&nbsp;<br>Il reviendra donc au Gouvernement de proc&#x00E9;der &#x00E0; l&#x2019;abondement de cr&#x00E9;dits n&#x00E9;cessaire.</p>", "annexeExposeSommaire": {"@xmlns:xsi": "http://www.w3.org/2001/XMLSchema-instance", "@xsi:nil": "true"}}}, "cycleDeVie": {"dateDepot": "2024-10-24", "datePublication": "2025-02-18", "soumisArticle40": "true", "etatDesTraitements": {"etat": {"code": "ET", "libelle": "En traitement"}, "sousEtat": {"code": "R", "libelle": "R"}}, "dateSort": {"@xmlns:xsi": "http://www.w3.org/2001/XMLSchema-instance", "@xsi:nil": "true"}, "sort": {"@xmlns:xsi": "http://www.w3.org/2001/XMLSchema-instance", "@xsi:nil": "true"}}, "representations": {"representation": {"nom": "PDF", "typeMime": {"type": "application", "subType": "PDF"}, "statutRepresentation": {"verbatim": "true", "canonique": "true", "officielle": "true", "transcription": "false", "enregistrement": "false"}, "repSource": {"@xmlns:xsi": "http://www.w3.org/2001/XMLSchema-instance", "@xsi:nil": "true"}, "offset": {"@xmlns:xsi": "http://www.w3.org/2001/XMLSchema-instance", "@xsi:nil": "true"}, "contenu": {"documentURI": "/base/AMANR5L17PO838901B0324P2D1N000151?format=pdf"}, "dateDispoRepresentation": {"@xmlns:xsi": "http://www.w3.org/2001/XMLSchema-instance", "@xsi:nil": "true"}}}, "seanceDiscussionRef": {"@xmlns:xsi": "http://www.w3.org/2001/XMLSchema-instance", "@xsi:nil": "true"}, "article99": "false", "loiReference": {"codeLoi": "E", "divisionCodeLoi": "67"}, "discussionCommune": {"@xmlns:xsi": "http://www.w3.org/2001/XMLSchema-instance", "@xsi:nil": "true"}, "discussionIdentique": {"@xmlns:xsi": "http://www.w3.org/2001/XMLSchema-instance", "@xsi:nil": "true"}, "accordGouvernementDepotHorsDelai": "Sans objet"}}