{"amendement": {"@xmlns": "http://schemas.assemblee-nationale.fr/referentiel", "uid": "AMANR5L17PO59051B0134P0D1N000228", "chronotag": "1739874521026", "legislature": "17", "identification": {"numeroLong": "CL228", "numeroOrdreDepot": "228", "prefixeOrganeExamen": "CION_LOIS", "numeroRect": "0"}, "examenRef": "EXANR5L17PO59051B0134P0D1", "texteLegislatifRef": "PIONANR5L17B0134", "triAmendement": "aeaaaaaaaaaaaaaaaaaaaaaaaaaaaaaaaaaaaaaaaaaaaaaaaabu", "cardinaliteAmdtMultiples": "1", "amendementParentRef": {"@xmlns:xsi": "http://www.w3.org/2001/XMLSchema-instance", "@xsi:nil": "true"}, "signataires": {"auteur": {"typeAuteur": "D\u00e9put\u00e9", "gouvernementRef": {"@xmlns:xsi": "http://www.w3.org/2001/XMLSchema-instance", "@xsi:nil": "true"}, "acteurRef": "PA722150", "groupePolitiqueRef": "PO840056", "auteurRapporteurOrganeRef": {"@xmlns:xsi": "http://www.w3.org/2001/XMLSchema-instance", "@xsi:nil": "true"}}, "cosignataires": {"acteurRef": ["PA643175", "PA607395", "PA720362", "PA642695", "PA793210"]}, "suffixe": {"@xmlns:xsi": "http://www.w3.org/2001/XMLSchema-instance", "@xsi:nil": "true"}, "libelle": "M.&#160;Houli&#233;,  Mme&#160;Dupont, M.&#160;Travert, M.&#160;Belhaddad, M.&#160;Bothorel et M.&#160;Panifous"}, "pointeurFragmentTexte": {"partieAmendableRef": {"@xmlns:xsi": "http://www.w3.org/2001/XMLSchema-instance", "@xsi:nil": "true"}, "division": {"titre": "Article PREMIER", "articleDesignationCourte": "ART. PREMIER", "articleDesignation": "ARTICLE PREMIER", "type": "ARTICLE", "avant_A_Apres": "A", "divisionRattachee": {"@xmlns:xsi": "http://www.w3.org/2001/XMLSchema-instance", "@xsi:nil": "true"}, "articleAdditionnel": "false", "chapitreAdditionnel": "false", "urlDivisionTexteVise": "/17/textes/0134.asp#D_Article_1er"}, "amendementStandard": {"alinea": {"@xmlns:xsi": "http://www.w3.org/2001/XMLSchema-instance", "@xsi:nil": "true"}}}, "corps": {"cartoucheInformatif": {"@xmlns:xsi": "http://www.w3.org/2001/XMLSchema-instance", "@xsi:nil": "true"}, "contenuAuteur": {"dispositif": "<p style=\"text-align: justify;\">R&#x00E9;diger ainsi cet article&nbsp;:</p><p style=\"text-align: justify;\">&#x00AB;&nbsp;L&#x2019;article&nbsp;L.&nbsp;613&#x2011;2 du code de la s&#x00E9;curit&#x00E9; int&#x00E9;rieure est compl&#x00E9;t&#x00E9; par un alin&#x00E9;a ainsi r&#x00E9;dig&#x00E9;&nbsp;:</p><p style=\"text-align: justify;\">&#x00AB;&nbsp;&#x00AB;&nbsp;Par d&#x00E9;rogation &#x00E0; l&#x2019;article&nbsp;L.&nbsp;122&#x2011;1, dans les d&#x00E9;partements de la r&#x00E9;gion &#x00CE;le-de-France, la constatation de circonstances particuli&#x00E8;res li&#x00E9;es &#x00E0; l&#x2019;existence de menaces graves pour la s&#x00E9;curit&#x00E9; publique ou l&#x2019;institution d&#x2019;un p&#x00E9;rim&#x00E8;tre de protection autorisant les agents des services internes de s&#x00E9;curit&#x00E9; de la SNCF et de la R&#x00E9;gie autonome des transports parisiens &#x00E0; proc&#x00E9;der, dans les conditions pr&#x00E9;vues au deuxi&#x00E8;me alin&#x00E9;a du pr&#x00E9;sent article, &#x00E0; des palpations de s&#x00E9;curit&#x00E9;, rel&#x00E8;ve de la comp&#x00E9;tence du pr&#x00E9;fet de police.&nbsp;&#x00BB;</p>", "avantAppel": {"@xmlns:xsi": "http://www.w3.org/2001/XMLSchema-instance", "@xsi:nil": "true"}, "exposeSommaire": "<p>Le pr&#x00E9;sent amendement tend &#x00E0; r&#x00E9;&#x00E9;crire l&#x2019;article 1er&nbsp;pour substituer au dispositif propos&#x00E9; d&#x2019;extension significative des facult&#x00E9;s des agents de s&#x00FB;ret&#x00E9; de la SNCF et de la RATP de proc&#x00E9;der &#x00E0; des palpations de s&#x00E9;curit&#x00E9;, un dispositif visant &#x00E0; rationaliser le cadre juridique d&#x2019;autorisation de ces palpations en r&#x00E9;gion &#x00CE;le-de-France.<br>&nbsp;<br>Le cadre juridique actuel n&#x2019;est pas pleinement satisfaisant, dans la mesure o&#x00F9; ces palpations, ne sont autoris&#x00E9;es que sur le fondement d&#x2019;un arr&#x00EA;t&#x00E9; du repr&#x00E9;sentant de l&#x2019;&#x00C9;tat dans le d&#x00E9;partement instituant un p&#x00E9;rim&#x00E8;tre de s&#x00E9;curit&#x00E9; ou constatant l&#x2019;existence de circonstances particuli&#x00E8;res li&#x00E9;es &#x00E0; l'existence de menaces graves pour la s&#x00E9;curit&#x00E9; publique.<br>&nbsp;<br>Or, il appara&#x00EE;t bien souvent en pratique qu&#x2019;en fonction des d&#x00E9;partements concern&#x00E9;s, ces arr&#x00EA;t&#x00E9;s sont d&#x00E9;livr&#x00E9;s &#x00E0; des fr&#x00E9;quences diverses, avec des port&#x00E9;es divergentes et pour des dur&#x00E9;es parfois trop br&#x00E8;ves au regard de la stabilit&#x00E9; des situations op&#x00E9;rationnelles auxquelles sont confront&#x00E9;s les agents de s&#x00FB;ret&#x00E9;. C&#x2019;est tout particuli&#x00E8;rement le cas en r&#x00E9;gion &#x00CE;le-de-France, qui implique l&#x2019;intervention d&#x2019;un grand nombre d&#x2019;acteurs pr&#x00E9;fectoraux, alors m&#x00EA;me que les enjeux de s&#x00FB;ret&#x00E9; y sont particuli&#x00E8;rement pr&#x00E9;gnants. Pour m&#x00E9;moire en effet, selon le minist&#x00E8;re de l&#x2019;int&#x00E9;rieur, ce territoire concentrait&nbsp;62% des vols et violences recens&#x00E9;s dans les transports &#x00E0; l&#x2019;&#x00E9;chelle nationale en&nbsp;2022.<br>&nbsp;<br>La solution propos&#x00E9;e &#x00E0; l&#x2019;article 1er, qui pr&#x00E9;voit de conf&#x00E9;rer aux agents de s&#x00FB;ret&#x00E9; de la SNCF et de la RATP la facult&#x00E9; de proc&#x00E9;der &#x00E0; de telles palpations, en l&#x2019;absence de toute autorisation pr&#x00E9;fectorale, &#x00E0; la seule condition que des &#x00E9;l&#x00E9;ments objectifs laissent &#x00E0; penser qu&#x2019;une personne pourrait d&#x00E9;tenir des objets susceptibles de pr&#x00E9;senter un risque pour la s&#x00E9;curit&#x00E9; des personnes ou des biens, revient cependant &#x00E0; leur confier un tr&#x00E8;s important pouvoir d&#x2019;appr&#x00E9;ciation. Au surplus, ce dispositif n&#x2019;int&#x00E8;gre pas la garantie, pr&#x00E9;vue en l&#x2019;&#x00E9;tat du droit, selon laquelle la palpation doit &#x00EA;tre effectu&#x00E9;e par une personne de m&#x00EA;me sexe que la personne qui en fait l&#x2019;objet.<br>&nbsp;<br>Ainsi, le dispositif ne r&#x00E9;pond pas aux exigences constitutionnelles en mati&#x00E8;re de protection du droit &#x00E0; la vie priv&#x00E9;e et &#x00E0; la libert&#x00E9; d&#x2019;aller et de venir, et se heurte &#x00E0; l'interdiction de d&#x00E9;l&#x00E9;guer &#x00E0; des personnes priv&#x00E9;es des comp&#x00E9;tences de police administrative g&#x00E9;n&#x00E9;rale inh&#x00E9;rentes &#x00E0; l'exercice de la &#x00AB; force publique &#x00BB; n&#x00E9;cessaire &#x00E0; la garantie des droits d&#x00E9;coulant de l&#x2019;article 12 de la D&#x00E9;claration des droits de l&#x2019;Homme et du Citoyen de 1789.<br>&nbsp;<br>C&#x2019;est la raison pour laquelle le pr&#x00E9;sent amendement propose une solution alternative consistant, sans remettre en cause les pr&#x00E9;rogatives de l&#x2019;autorit&#x00E9; pr&#x00E9;fectorale, de renforcer son efficacit&#x00E9; en confiant au seul pr&#x00E9;fet de police, qui dispose d&#x2019;une vision globale des enjeux de s&#x00FB;ret&#x00E9; dans la r&#x00E9;gion, le soin de prendre les arr&#x00EA;t&#x00E9;s autorisant les agents de s&#x00FB;ret&#x00E9; de la SNCF et de la RATP pour l&#x2019;ensemble de la r&#x00E9;gion &#x00CE;le-de-France. Une telle solution permet de clarifier une r&#x00E9;partition des r&#x00F4;les complexe, dans laquelle le pr&#x00E9;fet de police dispose d&#x00E9;j&#x00E0; de cette comp&#x00E9;tence sur l&#x2019;ensemble du r&#x00E9;seau ferr&#x00E9; dans la r&#x00E9;gion.<br>&nbsp;<br>Enfin, le pr&#x00E9;sent amendement tend &#x00E0; supprimer le dispositif permettant aux agents de s&#x00FB;ret&#x00E9; de la SNCF et de la RATP de saisir des objets au seul motif qu&#x2019;ils pourraient pr&#x00E9;senter un caract&#x00E8;re dangereux, g&#x00EA;nant ou incommodant pour les voyageurs et ce ind&#x00E9;pendamment de la l&#x00E9;galit&#x00E9; de leur port ou de leur transport. La saisie et la confiscation d&#x2019;objets constitue, en effet, une pr&#x00E9;rogative exclusive de l&#x2019;autorit&#x00E9; judiciaire.<br>&nbsp;</p>", "annexeExposeSommaire": {"@xmlns:xsi": "http://www.w3.org/2001/XMLSchema-instance", "@xsi:nil": "true"}}}, "cycleDeVie": {"dateDepot": "2024-11-23", "datePublication": "2024-11-27", "soumisArticle40": "false", "etatDesTraitements": {"etat": {"code": "DI", "libelle": "Discut\u00e9"}, "sousEtat": {"code": "DI", "libelle": "Rejet\u00e9"}}, "dateSort": "2024-11-27T12:09:50+01:00", "sort": "Rejet\u00e9"}, "representations": {"representation": {"nom": "PDF", "typeMime": {"type": "application", "subType": "PDF"}, "statutRepresentation": {"verbatim": "true", "canonique": "true", "officielle": "true", "transcription": "false", "enregistrement": "false"}, "repSource": {"@xmlns:xsi": "http://www.w3.org/2001/XMLSchema-instance", "@xsi:nil": "true"}, "offset": {"@xmlns:xsi": "http://www.w3.org/2001/XMLSchema-instance", "@xsi:nil": "true"}, "contenu": {"documentURI": "/base/AMANR5L17PO59051B0134P0D1N000228?format=pdf"}, "dateDispoRepresentation": {"@xmlns:xsi": "http://www.w3.org/2001/XMLSchema-instance", "@xsi:nil": "true"}}}, "seanceDiscussionRef": {"@xmlns:xsi": "http://www.w3.org/2001/XMLSchema-instance", "@xsi:nil": "true"}, "article99": "false", "loiReference": {"codeLoi": {"@xmlns:xsi": "http://www.w3.org/2001/XMLSchema-instance", "@xsi:nil": "true"}, "divisionCodeLoi": "dc1"}, "discussionCommune": {"idDiscussion": "28318", "typePosition": "Dernier"}, "discussionIdentique": {"idDiscussion": "74406", "typePosition": "Dernier"}, "accordGouvernementDepotHorsDelai": "Sans objet"}}